<?xml version="1.0" encoding="UTF-8"?>
<flow id="7705c2f1-c14f-4c54-9faa-bb437654f750">
  <descriptionCdata><![CDATA[7705c2f1-c14f-4c54-9faa-bb437654f750.85d4a496-d300-427b-87a2-9bddca6b7d0c.prompt=Seleziona ogni volta 1 a 5 
7705c2f1-c14f-4c54-9faa-bb437654f750.c860356e-8d54-4c42-b9e7-84efa9eef872.description=Iterates through a selection list. If the list changes while running, the updates will be appended to the list.\n\n<pre>\nInputs\:\nlist - The selection list to iterate through.\n\nReturns\:\nThe current element of the list, if the response is has more\n\nResponses\:\nhas more - Another value was in the list, and has been returned.\nhas no more - The iterator has gone fully through the list. This response will only be returned once per iteration through the list, a subsequent call to the Iterator will restart the Iteration through the list.\nfailure - failed to process the list.\n\nNote\: Where the iterator is in the list is tracked by each step's unique id. Therefore you can iterate on the same list from multiple steps simultaneously.\n\nWARNING\: Any step that will use the results of this Iterator operation will, by default, attempt to assign that step's inputs from a flow variable. If this is left checked, then the first element of the iterator will be used for every cycle of iteration..\n</pre>
7705c2f1-c14f-4c54-9faa-bb437654f750.description=<pre>\nun flusso che score una selection Lista creata amano nella configuratin del progetto e crei un file.txt, sotto la cartella creata dal flusso 4 per ogni elemento della lista \nIl file.txt dovr\u00E0 essere denominato con il valore letto e contenere il numero corrispondente\ndell\u2019elemento nella lista.\nEsempio\:\nSelection List\:\nCiao\nSono\nUna\nLista\nil file \u201CLista.txt\u201D dovr\u00E0 contenere il valore 4 essendo il quarto elemento della lista.\nper il momento e un flusso infinito che soprasrive se richiesto il content dei file\nInputs\:\nNo input \n\nResponses;\n  no response\n</pre>
7705c2f1-c14f-4c54-9faa-bb437654f750.ff660ef4-ceb7-44a5-8276-c8855d1d0d17.description=<pre>This operation writes the data from "contents" input to the requested file. The operation can be used to overwrite existing content of the file, append extra lines to it or even create a new file.\n\nInputs\:\n    source -  Full path to file. If the file does not exist it is created first.\n    contents - The content that should be written to the file. This input field can contain more lines, separated by a delimiter. If it contains the new line character (\\n or \\r\\n), but this is not the delimiter, this character will be escaped and written to file.  \nExample\: "This is line no. 01\\nThis is line no. 2\\n" where \\n is the delimiter.\n    delimiter - Specifies the newline delimiter that is used to split the "contents" input field into separate lines that will be further written to the given file.\nExamples\: \\n, \\r\\n, etc\n    characterSet - The character encoding used to write to the file. \nDefault\: UTF-8. \nValid values\: windows-1252, UTF-16, UTF-16BE,  ISO-8859-1, US-ASCII, Shift_JIS etc.\n    overwrite - Specifies whether to overwrite the file or append to it. \nDefault\: true. \nValid values\: true, false or the empty string. If this is left empty, the file will be overwritten.\n\nResults\:\n    returnResult - This is the primary output. It contains the "success" confirmation message if the operation successfully completes, or an exception message otherwise.\n    returnCode - It has the value 0 if the operation successfully completes and 1 otherwise.\n    exception - This contains an exception message if the operation fails.\n\nResponses\:\n    success - File/directory was written successfully.\n    failure - Unable to write to file/directory, empty contents or source.\n\nExamples\:\n1. This is a valid input example for using this operation on Windows\:\n    source\: C\:\\Program Files\\example.txt\n    contents\: line1,line2,line3\n    delimiter\: ,\n\n2. This is a valid input example for using this operation on Linux\:\n    source\: /root/example.txt\n    contents\: line1,line2,line3\n    delimiter\: ,\n</pre>
]]></descriptionCdata>
  <annotation>7705c2f1-c14f-4c54-9faa-bb437654f750.description</annotation>
  <name>7-Crea File Da Selection List Flow</name>
  <categories/>
  <inputs/>
  <possibleResponses>
    <opResponse id="3493740a-cafa-4044-9d2e-05238295f8a9">
      <annotation></annotation>
      <name>unknown</name>
      <isDefault>false</isDefault>
      <onFailure>false</onFailure>
      <type>NO_ACTION_TAKEN</type>
      <matchRules/>
    </opResponse>
  </possibleResponses>
  <availableResultExpressions/>
  <resultExpression id="cb02251e-5a11-4ed5-95c9-ad3e7b142055">
    <annotation></annotation>
    <name>FailureMessage</name>
    <fieldName>FailureMessage</fieldName>
    <sourceType>RAWRESULT</sourceType>
    <filters/>
  </resultExpression>
  <iconSpec id="e9c58150-93f0-44e0-a2e9-7527e73c0ab1">
    <baseIcon>flow.png</baseIcon>
    <basePath>System</basePath>
    <readOnly>false</readOnly>
    <layers/>
  </iconSpec>
  <callouts/>
  <checkPointFlow>true</checkPointFlow>
  <compatibleRuntimeContext>false</compatibleRuntimeContext>
  <historyCheckPointFlow>true</historyCheckPointFlow>
  <steps>
    <step id="c860356e-8d54-4c42-b9e7-84efa9eef872">
      <annotation>7705c2f1-c14f-4c54-9faa-bb437654f750.c860356e-8d54-4c42-b9e7-84efa9eef872.description</annotation>
      <name>Selection List Iterate</name>
      <bounds>
        <x>138.0</x>
        <y>213.0</y>
      </bounds>
      <layer>-1</layer>
      <hideInbound>false</hideInbound>
      <addResultToRunContext>false</addResultToRunContext>
      <isCriticalStep>false</isCriticalStep>
      <isNonBlocking>false</isNonBlocking>
      <isParallelStep>false</isParallelStep>
      <isSingleResponse>false</isSingleResponse>
      <recordInHistory>false</recordInHistory>
      <recordRawOutput>true</recordRawOutput>
      <recordPrimaryOutput>true</recordPrimaryOutput>
      <checkPointStep>true</checkPointStep>
      <historyCheckPointStep>true</historyCheckPointStep>
      <scriptResultStep>false</scriptResultStep>
      <userPrompt></userPrompt>
      <bindings>
        <userInputBinding id="85d4a496-d300-427b-87a2-9bddca6b7d0c">
          <annotation></annotation>
          <fromContextKey>Lista</fromContextKey>
          <assignFromContext>false</assignFromContext>
          <assignToContext>true</assignToContext>
          <inputType>STRING</inputType>
          <isList>false</isList>
          <required>true</required>
          <isPersisted>true</isPersisted>
          <inputSymbol>list</inputSymbol>
          <listDelimiter>,</listDelimiter>
          <record>false</record>
          <prompt>7705c2f1-c14f-4c54-9faa-bb437654f750.85d4a496-d300-427b-87a2-9bddca6b7d0c.prompt</prompt>
          <isMultiSelect>false</isMultiSelect>
          <link>
            <refId>f3dc7cae-1195-4a5b-948a-ea849b93e2b6</refId>
            <refName>Lista</refName>
          </link>
          <sourceDelimiter>|</sourceDelimiter>
        </userInputBinding>
        <staticBinding id="b35d3151-40f3-40d6-a7be-de87790a7290">
          <annotation></annotation>
          <toContextKey></toContextKey>
          <fromContextKey></fromContextKey>
          <assignFromContext>false</assignFromContext>
          <assignToContext>false</assignToContext>
          <inputType>STRING</inputType>
          <recordKey></recordKey>
          <isList>false</isList>
          <required>false</required>
          <isPersisted>true</isPersisted>
          <inputSymbol>separator</inputSymbol>
          <listDelimiter></listDelimiter>
          <value>|</value>
          <record>false</record>
        </staticBinding>
      </bindings>
      <transitions>
        <transition id="d6455e31-2d33-41ed-80d0-e0e0c397f5f1">
          <annotation></annotation>
          <name>failure</name>
          <command>NEXT</command>
          <linkMode>false</linkMode>
          <responseSymbol>failure</responseSymbol>
          <shouldHandoff>false</shouldHandoff>
          <transitionValue>0.0</transitionValue>
          <destination>
            <refId>de3d161a-353a-46a3-bb34-9c7bccc9040b</refId>
          </destination>
          <source>
            <refId>c860356e-8d54-4c42-b9e7-84efa9eef872</refId>
          </source>
          <positions>
            <point>
              <x>188.0</x>
              <y>247.0</y>
            </point>
            <point>
              <x>192.0</x>
              <y>444.0</y>
            </point>
          </positions>
          <labelPosition>
            <x>333.0</x>
            <y>0.0</y>
          </labelPosition>
        </transition>
        <transition id="27dc40fc-99ad-4673-a985-609c2b26f95e">
          <annotation></annotation>
          <name>no more</name>
          <command>NEXT</command>
          <linkMode>false</linkMode>
          <responseSymbol>no more</responseSymbol>
          <shouldHandoff>false</shouldHandoff>
          <transitionValue>0.0</transitionValue>
          <destination>
            <refId>de3d161a-353a-46a3-bb34-9c7bccc9040b</refId>
          </destination>
          <source>
            <refId>c860356e-8d54-4c42-b9e7-84efa9eef872</refId>
          </source>
          <positions>
            <point>
              <x>188.0</x>
              <y>247.0</y>
            </point>
            <point>
              <x>245.212871206157</x>
              <y>309.48012595085373</y>
            </point>
            <point>
              <x>246.77682509212883</x>
              <y>386.50485483496783</y>
            </point>
            <point>
              <x>192.0</x>
              <y>444.0</y>
            </point>
          </positions>
          <labelPosition>
            <x>333.0</x>
            <y>0.0</y>
          </labelPosition>
        </transition>
        <transition id="b1c0234d-0f8e-4142-a82f-9bc4518976c1">
          <annotation></annotation>
          <name>has more</name>
          <command>NEXT</command>
          <linkMode>false</linkMode>
          <responseSymbol>has more</responseSymbol>
          <shouldHandoff>false</shouldHandoff>
          <transitionValue>0.0</transitionValue>
          <destination>
            <refId>ff660ef4-ceb7-44a5-8276-c8855d1d0d17</refId>
          </destination>
          <source>
            <refId>c860356e-8d54-4c42-b9e7-84efa9eef872</refId>
          </source>
          <positions>
            <point>
              <x>188.0</x>
              <y>247.0</y>
            </point>
            <point>
              <x>686.0</x>
              <y>257.0</y>
            </point>
          </positions>
          <labelPosition>
            <x>333.0</x>
            <y>0.0</y>
          </labelPosition>
        </transition>
      </transitions>
      <properties/>
      <opRef>
        <refId>f7c85459-a95f-40a7-bbe0-bbeff99c8c0b</refId>
      </opRef>
      <assignments>
        <flowVariableAssignment id="72d1d46a-6610-46d4-8ce6-84db641743bb">
          <annotation></annotation>
          <name>assignment</name>
          <action>OVERWRITE</action>
          <assignmentTargetType>FLOW_VARIABLE</assignmentTargetType>
          <contextKey>Titolo</contextKey>
          <expression id="aa3f0815-4249-40b5-9279-424ed9051342">
            <annotation></annotation>
            <name>Result Field: resultString</name>
            <fieldName>resultString</fieldName>
            <sourceType>RAWRESULT</sourceType>
            <filters/>
          </expression>
        </flowVariableAssignment>
      </assignments>
      <throttleSize>0</throttleSize>
    </step>
    <step id="ff660ef4-ceb7-44a5-8276-c8855d1d0d17">
      <annotation>7705c2f1-c14f-4c54-9faa-bb437654f750.ff660ef4-ceb7-44a5-8276-c8855d1d0d17.description</annotation>
      <name>Write to File</name>
      <bounds>
        <x>636.0</x>
        <y>223.0</y>
      </bounds>
      <layer>-1</layer>
      <hideInbound>false</hideInbound>
      <addResultToRunContext>false</addResultToRunContext>
      <isCriticalStep>false</isCriticalStep>
      <isNonBlocking>false</isNonBlocking>
      <isParallelStep>false</isParallelStep>
      <isSingleResponse>false</isSingleResponse>
      <recordInHistory>false</recordInHistory>
      <recordRawOutput>true</recordRawOutput>
      <recordPrimaryOutput>true</recordPrimaryOutput>
      <checkPointStep>true</checkPointStep>
      <historyCheckPointStep>true</historyCheckPointStep>
      <scriptResultStep>false</scriptResultStep>
      <userPrompt></userPrompt>
      <bindings>
        <staticBinding id="4e2b0baf-a261-4980-9c87-7de57961cea7">
          <annotation></annotation>
          <toContextKey></toContextKey>
          <fromContextKey></fromContextKey>
          <assignFromContext>false</assignFromContext>
          <assignToContext>false</assignToContext>
          <inputType>STRING</inputType>
          <isList>false</isList>
          <required>true</required>
          <isPersisted>true</isPersisted>
          <inputSymbol>source</inputSymbol>
          <listDelimiter>,</listDelimiter>
          <value>C:\HPOO_TEST\pop\pop.txt</value>
          <record>false</record>
        </staticBinding>
        <staticBinding id="d6e1374b-8c82-4575-9f84-5a756368e2d9">
          <annotation></annotation>
          <toContextKey></toContextKey>
          <fromContextKey></fromContextKey>
          <assignFromContext>false</assignFromContext>
          <assignToContext>false</assignToContext>
          <inputType>STRING</inputType>
          <isList>false</isList>
          <required>true</required>
          <isPersisted>true</isPersisted>
          <inputSymbol>contents</inputSymbol>
          <listDelimiter>,</listDelimiter>
          <value>${Titolo}</value>
          <record>false</record>
        </staticBinding>
        <staticBinding id="165b8cee-aeaa-494f-afa7-e05b13614cd3">
          <annotation></annotation>
          <assignFromContext>false</assignFromContext>
          <assignToContext>false</assignToContext>
          <inputType>STRING</inputType>
          <isList>false</isList>
          <required>false</required>
          <isPersisted>true</isPersisted>
          <inputSymbol>delimiter</inputSymbol>
          <listDelimiter>,</listDelimiter>
          <record>false</record>
        </staticBinding>
        <staticBinding id="197018df-7067-448c-85d5-cb7268521d1f">
          <annotation></annotation>
          <assignFromContext>false</assignFromContext>
          <assignToContext>false</assignToContext>
          <inputType>STRING</inputType>
          <isList>false</isList>
          <required>false</required>
          <isPersisted>true</isPersisted>
          <inputSymbol>characterSet</inputSymbol>
          <listDelimiter>,</listDelimiter>
          <record>false</record>
        </staticBinding>
        <userInputBinding id="8953c735-a918-482b-9f84-a40eb8a71296">
          <annotation></annotation>
          <assignFromContext>false</assignFromContext>
          <assignToContext>false</assignToContext>
          <inputType>STRING</inputType>
          <isList>false</isList>
          <required>false</required>
          <isPersisted>true</isPersisted>
          <inputSymbol>overwrite</inputSymbol>
          <listDelimiter>,</listDelimiter>
          <record>false</record>
          <prompt></prompt>
          <isMultiSelect>false</isMultiSelect>
          <link>
            <refId>362bc113-e130-45d5-be90-832d5de87730</refId>
            <refName>Boolean</refName>
          </link>
          <sourceDelimiter>|</sourceDelimiter>
        </userInputBinding>
      </bindings>
      <transitions>
        <transition id="9ce8229e-6c51-4543-8b3f-bdde3d4c38b4">
          <annotation></annotation>
          <name>success</name>
          <command>NEXT</command>
          <linkMode>false</linkMode>
          <responseSymbol>success</responseSymbol>
          <shouldHandoff>false</shouldHandoff>
          <transitionValue>0.0</transitionValue>
          <destination>
            <refId>c860356e-8d54-4c42-b9e7-84efa9eef872</refId>
          </destination>
          <source>
            <refId>ff660ef4-ceb7-44a5-8276-c8855d1d0d17</refId>
          </source>
          <positions>
            <point>
              <x>686.0</x>
              <y>257.0</y>
            </point>
            <point>
              <x>626.5139997751967</x>
              <y>230.8004622702098</y>
            </point>
            <point>
              <x>248.48981393092555</x>
              <y>223.20961516490317</y>
            </point>
            <point>
              <x>188.0</x>
              <y>247.0</y>
            </point>
          </positions>
          <labelPosition>
            <x>333.0</x>
            <y>0.0</y>
          </labelPosition>
        </transition>
        <transition id="0c715a78-3106-4e09-b7d6-18a926ce4fe2">
          <annotation></annotation>
          <name>failure</name>
          <command>NEXT</command>
          <linkMode>false</linkMode>
          <responseSymbol>failure</responseSymbol>
          <shouldHandoff>false</shouldHandoff>
          <transitionValue>0.0</transitionValue>
          <destination>
            <refId>de3d161a-353a-46a3-bb34-9c7bccc9040b</refId>
          </destination>
          <source>
            <refId>ff660ef4-ceb7-44a5-8276-c8855d1d0d17</refId>
          </source>
          <positions>
            <point>
              <x>686.0</x>
              <y>257.0</y>
            </point>
            <point>
              <x>192.0</x>
              <y>444.0</y>
            </point>
          </positions>
          <labelPosition>
            <x>333.0</x>
            <y>0.0</y>
          </labelPosition>
        </transition>
      </transitions>
      <properties/>
      <opRef>
        <refId>48aa1efc-f914-4be6-b68b-8d5d41753792</refId>
      </opRef>
      <assignments/>
      <throttleSize>0</throttleSize>
    </step>
    <returnStep id="de3d161a-353a-46a3-bb34-9c7bccc9040b">
      <annotation></annotation>
      <name>No Action Taken : unknown</name>
      <bounds>
        <x>142.0</x>
        <y>410.0</y>
      </bounds>
      <layer>-1</layer>
      <hideInbound>false</hideInbound>
      <addResultToRunContext>false</addResultToRunContext>
      <isCriticalStep>false</isCriticalStep>
      <isNonBlocking>false</isNonBlocking>
      <isParallelStep>false</isParallelStep>
      <isSingleResponse>false</isSingleResponse>
      <recordInHistory>false</recordInHistory>
      <recordRawOutput>true</recordRawOutput>
      <recordPrimaryOutput>true</recordPrimaryOutput>
      <checkPointStep>true</checkPointStep>
      <historyCheckPointStep>true</historyCheckPointStep>
      <scriptResultStep>false</scriptResultStep>
      <userPrompt></userPrompt>
      <bindings/>
      <transitions>
        <transition id="86318d86-0669-4944-a273-94286d464ef9">
          <annotation></annotation>
          <name>return</name>
          <command>NEXT</command>
          <linkMode>false</linkMode>
          <responseSymbol>unknown</responseSymbol>
          <shouldHandoff>false</shouldHandoff>
          <transitionValue>0.0</transitionValue>
          <destination>
            <refId>de3d161a-353a-46a3-bb34-9c7bccc9040b</refId>
          </destination>
          <source>
            <refId>de3d161a-353a-46a3-bb34-9c7bccc9040b</refId>
          </source>
          <positions/>
        </transition>
      </transitions>
      <properties/>
      <returnStepType>NO_ACTION_TAKEN</returnStepType>
      <assignments/>
    </returnStep>
  </steps>
  <startSteps>c860356e-8d54-4c42-b9e7-84efa9eef872</startSteps>
</flow>